mixsol/__init__.py
mixsol/components.py
mixsol/digraph.py
mixsol/helpers.py
mixsol/mix.py
mixsol-0.7.2.dist-info/LICENSE
mixsol-0.7.2.dist-info/METADATA
mixsol-0.7.2.dist-info/WHEEL
mixsol-0.7.2.dist-info/top_level.txt
mixsol-0.7.2.dist-info/RECORD
