Metadata-Version: 2.1
Name: mixsol
Version: 0.7.2
Summary: Planning tool for combinatorial solution mixing. Reach target solutions from mixes of starting solutions, constrained by minimum pipetting volumes. Also aids in computing amounts of powdered reagents required to form solutions with target solutes + molarities.
Home-page: https://github.com/rekumar/mixsol
Download-URL: https://github.com/rekumar/mixsol/archive/refs/tags/v0.6.tar.gz
Author: Rishi E Kumar
Author-email: rishi42@gmail.com
License: GPLv3
Keywords: Chemistry,Mixing,Combinatoric,Planning,Dilution,Molarity,Solution
Platform: UNKNOWN
Classifier: Development Status :: 3 - Alpha
Classifier: Intended Audience :: Developers
Classifier: Intended Audience :: Science/Research
Classifier: Topic :: Scientific/Engineering :: Chemistry
Classifier: License :: OSI Approved :: GNU General Public License v3 (GPLv3)
Classifier: Programming Language :: Python :: 3
License-File: LICENSE
Requires-Dist: scipy
Requires-Dist: numpy
Requires-Dist: matplotlib
Requires-Dist: molmass
